fuckpad.py
fuckpad-1.0.0.data/scripts/fuckpad
fuckpad-1.0.0.dist-info/DESCRIPTION.rst
fuckpad-1.0.0.dist-info/METADATA
fuckpad-1.0.0.dist-info/RECORD
fuckpad-1.0.0.dist-info/WHEEL
fuckpad-1.0.0.dist-info/metadata.json
fuckpad-1.0.0.dist-info/top_level.txt
