Metadata-Version: 2.0
Name: fuckpad
Version: 1.0.0
Summary: Disables the loathsome Synaptics touchpad
Home-page: https://github.com/TadLeonard/fuckpad
Author: Tad Leonard
Author-email: tadfleonard@gmail.com
License: UNKNOWN
Download-URL: https://github.com/TadLeonard/fuckpad/archive/1.0.0.tar.gz
Platform: UNKNOWN
Classifier: Development Status :: 5 - Production/Stable
Classifier: Programming Language :: Python :: 3
Classifier: Programming Language :: Python :: 2
